LICENSE
MANIFEST.in
README.rst
pyproject.toml
setup.cfg
setup.py
django_resumes.egg-info/PKG-INFO
django_resumes.egg-info/SOURCES.txt
django_resumes.egg-info/dependency_links.txt
django_resumes.egg-info/requires.txt
django_resumes.egg-info/top_level.txt
resumes/__init__.py
resumes/admin.py
resumes/apps.py
resumes/models.py
resumes/tests.py
resumes/urls.py
resumes/views.py
resumes/migrations/0001_initial.py
resumes/migrations/__init__.py
resumes/templates/resumes/404.html
resumes/templates/resumes/base.html
resumes/templates/resumes/home.html
resumes/templates/resumes/index.html
resumes/templates/resumes/main.html
resumes/templates/resumes/resume.html
resumes/templates/resumes/base/base.html
resumes/templates/resumes/base/detail.html
resumes/templates/resumes/base/list.html
resumes/templates/resumes/base/new.html
resumes/templates/resumes/base/update.html
resumes/templates/resumes/basicinfomodel/detail.html
resumes/templates/resumes/basicinfomodel/list.html
resumes/templates/resumes/basicinfomodel/update.html
resumes/templates/resumes/educationmodel/detail.html
resumes/templates/resumes/educationmodel/list.html
resumes/templates/resumes/educationmodel/update.html
resumes/templates/resumes/partials/footer.html
resumes/templates/resumes/partials/header.html
resumes/templates/resumes/partials/nav.html
resumes/templates/resumes/skillmodel/detail.html
resumes/templates/resumes/skillmodel/list.html
resumes/templates/resumes/skillmodel/update.html
resumes/templates/resumes/workexperiencemodel/detail.html
resumes/templates/resumes/workexperiencemodel/list.html
resumes/templates/resumes/workexperiencemodel/update.html
resumes/templatetags/__init__.py
resumes/templatetags/resume_filter.py